textual_todo/__init__.py
textual_todo/datepicker.py
textual_todo/editabletext.py
textual_todo/py.typed
textual_todo/todo.py
textual_todo/todoitem.py
textual_todo-0.1.0.dist-info/LICENSE
textual_todo-0.1.0.dist-info/WHEEL
textual_todo-0.1.0.dist-info/entry_points.txt
textual_todo-0.1.0.dist-info/METADATA
textual_todo-0.1.0.dist-info/RECORD
